CreditScoringToolkit.py
tests/integration/test_autocreditscoring_pipeline.py
tests/integration/test_manual_pipeline.py
tests/unit/test_encoder.py
tests/unit/test_feature_selectors.py
tests/unit/test_normalizer.py
woe_credit_scoring/__init__.py
woe_credit_scoring/autocreditscoring.py
woe_credit_scoring/base.py
woe_credit_scoring/binning.py
woe_credit_scoring/encoder.py
woe_credit_scoring/normalizer.py
woe_credit_scoring/reporter.py
woe_credit_scoring/scoring.py
woe_credit_scoring-2.0.4.dist-info/licenses/LICENSE
woe_credit_scoring-2.0.4.dist-info/METADATA
woe_credit_scoring-2.0.4.dist-info/WHEEL
woe_credit_scoring-2.0.4.dist-info/top_level.txt
woe_credit_scoring-2.0.4.dist-info/RECORD
