Metadata-Version: 2.4
Name: woe_credit_scoring
Version: 2.0.4
Summary: A toolkit for Credit Scoring using Weight of Evidence (WoE) and Logistic Regression
Project-URL: Homepage, https://github.com/JGFuentesC/woe_credit_scoring
Project-URL: Bug Tracker, https://github.com/JGFuentesC/woe_credit_scoring/issues
Classifier: Programming Language :: Python :: 3
Classifier: License :: OSI Approved :: GNU General Public License v3 (GPLv3)
Classifier: Operating System :: OS Independent
Requires-Python: >=3.10
License-File: LICENSE
Requires-Dist: numpy>=1.21.0
Requires-Dist: pandas>=1.3.0
Requires-Dist: scikit-learn>=1.0.0
Requires-Dist: seaborn>=0.11.0
Requires-Dist: matplotlib>=3.4.0
Requires-Dist: scipy>=1.7.0
Dynamic: license-file
